<annotation>
	<folder>data</folder>
	<filename>001403.jpg</filename>
	<path>/home/mmwzj/WORK/kaiguan/csv/data/001403.jpg</path>
	<source>
		<database>Unknown</database>
	</source>
	<size>
		<width>333</width>
		<height>444</height>
		<depth>3</depth>
	</size>
	<segmented>0</segmented>
	<object>
		<name>switch</name>
		<pose>Unspecified</pose>
		<truncated>0</truncated>
		<difficult>0</difficult>
		<bndbox>
			<xmin>219</xmin>
			<ymin>191</ymin>
			<xmax>245</xmax>
			<ymax>267</ymax>
		</bndbox>
	</object>
	<object>
		<name>switch</name>
		<pose>Unspecified</pose>
		<truncated>0</truncated>
		<difficult>0</difficult>
		<bndbox>
			<xmin>242</xmin>
			<ymin>194</ymin>
			<xmax>280</xmax>
			<ymax>276</ymax>
		</bndbox>
	</object>
</annotation>
